Metadata-Version: 2.1
Name: genomelake
Version: 0.1.4
Summary: Simple and efficient random access to genomic data for deep learning models.
Home-page: https://github.com/kundajelab/genomelake
Author: Chuan-Sheng Foo
Author-email: csfoo@cs.stanford.edu
License: BSD-3
Keywords: deeplearning neuralnets genomics
Platform: UNKNOWN
Classifier: Development Status :: 3 - Alpha
Classifier: Intended Audience :: Science/Research
Classifier: Intended Audience :: Developers
Classifier: Topic :: Scientific/Engineering
Classifier: License :: OSI Approved :: BSD License
Classifier: Programming Language :: Python :: 2.7
Classifier: Programming Language :: Python :: 3.5
Classifier: Programming Language :: Python :: 3.6
Classifier: Operating System :: POSIX :: Linux
Provides-Extra: develop
